{"schema_version":1,"chunk_kind":"word_trace_bundle_chunk","verse_ref_key":"Deuteronomy/24/6","ref":{"book":"Deuteronomy","chapter":24,"verse":6},"word_traces":[{"record_kind":"WORD_TRACE","trace_version":"1.1.0","semantics_version":"1.1.0","render_version":"1.1.0","ref":{"book":"Deuteronomy","chapter":24,"verse":6,"token_index":1},"ref_key":"Deuteronomy/24/6/1","surface":"לֹא","token_ids":[390,1],"events":[{"kind":"LAMED.ENDPOINT","index":0,"tau":1,"source":"vm_event","payload":{"boundaryId":"ל:1:1","domain":"Ω","endpoint":"⊥","id":"ל:1:2"}},{"kind":"ALEPH.ALIAS","index":1,"tau":1,"source":"vm_event","payload":{"id":"א:1:1","left":"Ω","right":"ל:1:2"}}],"skeleton":["LAMED.ENDPOINT","ALEPH.ALIAS"],"flow":"ל endpoint bind ⇢ א alias","mode":"WORD","canonical_hash":"0688c8a031a3addb80e08a652a750f2f7cccf27b39647916437576e5347729f9"},{"record_kind":"WORD_TRACE","trace_version":"1.1.0","semantics_version":"1.1.0","render_version":"1.1.0","ref":{"book":"Deuteronomy","chapter":24,"verse":6,"token_index":2},"ref_key":"Deuteronomy/24/6/2","surface":"יַחֲבֹל","token_ids":[298,231,56,364],"events":[{"kind":"HET.COMPARTMENT","index":0,"tau":1,"source":"vm_event","payload":{"boundaryId":"ח:1:1","id":"ח:1:2","inside":"י:1:1","outside":"Ω"}},{"kind":"LAMED.ENDPOINT","index":1,"tau":1,"source":"vm_event","payload":{"boundaryId":"ל:1:1","domain":"ח:1:2","endpoint":"ב:1:1","id":"ל:1:2"}}],"skeleton":["HET.COMPARTMENT","LAMED.ENDPOINT"],"flow":"ח compartment ⇢ ל endpoint bind","mode":"WORD","canonical_hash":"dd638ff74b446614ac287cba5a26a199fc5b43314544d36aaeb6ba8618b4c3a0"},{"record_kind":"WORD_TRACE","trace_version":"1.1.0","semantics_version":"1.1.0","render_version":"1.1.0","ref":{"book":"Deuteronomy","chapter":24,"verse":6,"token_index":3},"ref_key":"Deuteronomy/24/6/3","surface":"רֵחַיִם","token_ids":[644,239,285,400],"events":[{"kind":"RESH.BOUNDARY_CLOSE","index":0,"tau":1,"source":"vm_event","payload":{"anchor":0,"id":"ר:1:1","inside":"Ω","outside":"Ω"}},{"kind":"HET.COMPARTMENT","index":1,"tau":1,"source":"vm_event","payload":{"boundaryId":"ח:1:1","id":"ח:1:2","inside":"ר:1:1","outside":"Ω"}},{"kind":"FINAL_MEM.CLOSE","index":2,"tau":1,"source":"derived_obligation","payload":{"action":"close","mode":"synthetic","obligation_kind":"MEM_ZONE"}}],"skeleton":["RESH.BOUNDARY_CLOSE","HET.COMPARTMENT","FINAL_MEM.CLOSE"],"flow":"ר boundary close ⇢ ח compartment ⇢ ם close mem-zone","mode":"WORD","canonical_hash":"97d9e16498fc8937d2197bdcf3829754db2819bda7ffff19e0683a9f1155b28b"},{"record_kind":"WORD_TRACE","trace_version":"1.1.0","semantics_version":"1.1.0","render_version":"1.1.0","ref":{"book":"Deuteronomy","chapter":24,"verse":6,"token_index":4},"ref_key":"Deuteronomy/24/6/4","surface":"וָרָכֶב","token_ids":[183,650,338,30],"events":[{"kind":"RESH.BOUNDARY_CLOSE","index":0,"tau":1,"source":"vm_event","payload":{"anchor":0,"id":"ר:1:1","inside":"ו:1:1","outside":"ו:1:2"}}],"skeleton":["RESH.BOUNDARY_CLOSE"],"flow":"ר boundary close","mode":"WORD","canonical_hash":"b43ddf04b5d14b0b77f57d250e627d0c51fda0dfa79f1968db1780536515a766"},{"record_kind":"WORD_TRACE","trace_version":"1.1.0","semantics_version":"1.1.0","render_version":"1.1.0","ref":{"book":"Deuteronomy","chapter":24,"verse":6,"token_index":5},"ref_key":"Deuteronomy/24/6/5","surface":"כִּי","token_ids":[331,280],"events":[],"skeleton":[],"flow":"(no semantic events)","mode":"WORD","canonical_hash":"eaa658c1397dd25c57d4bedd93de9259243c273ede81bcd6264e50284ec26f56"},{"record_kind":"WORD_TRACE","trace_version":"1.1.0","semantics_version":"1.1.0","render_version":"1.1.0","ref":{"book":"Deuteronomy","chapter":24,"verse":6,"token_index":6},"ref_key":"Deuteronomy/24/6/6","surface":"נֶפֶשׁ","token_ids":[455,545,720],"events":[{"kind":"NUN.SUPPORT_DEBT","index":0,"tau":1,"source":"derived_obligation","payload":{"action":"open","obligation_kind":"SUPPORT"}},{"kind":"PE.UTTER","index":1,"tau":1,"source":"vm_event","payload":{"id":"פ:1:1","payload":"⊥","source":"נ:1:1","target":"Ω"}},{"kind":"SHIN.FORK","index":2,"tau":1,"source":"vm_event","payload":{"active":"right","focus":"פ:1:1","id":"ש:1:4","left":"ש:1:2","right":"ש:1:3","spine":"ש:1:1"}},{"kind":"SPACE.SUPPORT_DISCHARGE","index":3,"tau":2,"source":"vm_event","payload":{"child":"נ:1:1","parent":"Ω"}}],"skeleton":["NUN.SUPPORT_DEBT","PE.UTTER","SHIN.FORK","SPACE.SUPPORT_DISCHARGE"],"flow":"נ support debt ⇢ פ utterance ⇢ ש fork route ⇢ □ boundary support discharge","mode":"WORD","canonical_hash":"81c7e205503be7dea41af84b144edf7c038f0cf467158de06ea777be512625e4"},{"record_kind":"WORD_TRACE","trace_version":"1.1.0","semantics_version":"1.1.0","render_version":"1.1.0","ref":{"book":"Deuteronomy","chapter":24,"verse":6,"token_index":7},"ref_key":"Deuteronomy/24/6/7","surface":"הוּא","token_ids":[136,193,1],"events":[{"kind":"HE.DECLARE","index":0,"tau":1,"source":"vm_event","payload":{"id":"ה:1:1","mode":"public","target":"Ω"}},{"kind":"ALEPH.ALIAS","index":1,"tau":1,"source":"vm_event","payload":{"id":"א:1:1","left":"Ω","right":"ו:1:1"}}],"skeleton":["HE.DECLARE","ALEPH.ALIAS"],"flow":"ה declare(public) ⇢ א alias","mode":"WORD","canonical_hash":"ba5c20c05b0cf4facfd6656e89cd1615277499c530ac3d3e2d8c3c2b39afe3e8"},{"record_kind":"WORD_TRACE","trace_version":"1.1.0","semantics_version":"1.1.0","render_version":"1.1.0","ref":{"book":"Deuteronomy","chapter":24,"verse":6,"token_index":8},"ref_key":"Deuteronomy/24/6/8","surface":"חֹבֵל","token_ids":[243,39,364],"events":[{"kind":"HET.COMPARTMENT","index":0,"tau":1,"source":"vm_event","payload":{"boundaryId":"ח:1:1","id":"ח:1:2","inside":"Ω","outside":"Ω"}},{"kind":"LAMED.ENDPOINT","index":1,"tau":1,"source":"vm_event","payload":{"boundaryId":"ל:1:1","domain":"ח:1:2","endpoint":"ב:1:1","id":"ל:1:2"}}],"skeleton":["HET.COMPARTMENT","LAMED.ENDPOINT"],"flow":"ח compartment ⇢ ל endpoint bind","mode":"WORD","canonical_hash":"713f0f97f8e86273d0d800a79e2b777a08c77cb7be4c0a9ab4a127d1854b9012"}],"word_phrase_roles":[{"ref_key":"Deuteronomy/24/6","word_index":1,"surface":"לֹא","primary_accent":{"word_index":1,"class":"NONE","codepoint":null,"name":null,"precedence":0,"observed_teamim":[]},"phrase_role":"HEAD","phrase_path":["w_1","n_1_2_join","n_1_3_join","n_1_4_split","n_1_8_split"],"clause_id":"C1","subclause_id":"C1.1","phrase_version":"phrase_tree.v1"},{"ref_key":"Deuteronomy/24/6","word_index":2,"surface":"יַחֲבֹ֥ל","primary_accent":{"word_index":2,"class":"CONJUNCTIVE","codepoint":"U+05A5","name":"merkha","precedence":1,"observed_teamim":["U+05A5"]},"phrase_role":"JOIN","phrase_path":["w_2","n_1_2_join","n_1_3_join","n_1_4_split","n_1_8_split"],"clause_id":"C1","subclause_id":"C1.1","phrase_version":"phrase_tree.v1"},{"ref_key":"Deuteronomy/24/6","word_index":3,"surface":"רֵחַ֖יִם","primary_accent":{"word_index":3,"class":"DISJUNCTIVE","codepoint":"U+0596","name":"tipcha","precedence":1,"observed_teamim":["U+0596"]},"phrase_role":"SPLIT","phrase_path":["w_3","n_1_3_join","n_1_4_split","n_1_8_split"],"clause_id":"C1","subclause_id":"C1.1","phrase_version":"phrase_tree.v1"},{"ref_key":"Deuteronomy/24/6","word_index":4,"surface":"וָרָ֑כֶב","primary_accent":{"word_index":4,"class":"DISJUNCTIVE","codepoint":"U+0591","name":"etnahta","precedence":2,"observed_teamim":["U+0591"]},"phrase_role":"SPLIT","phrase_path":["w_4","n_1_4_split","n_1_8_split"],"clause_id":"C1","subclause_id":"C1.2","phrase_version":"phrase_tree.v1"},{"ref_key":"Deuteronomy/24/6","word_index":5,"surface":"כִּי","primary_accent":{"word_index":5,"class":"NONE","codepoint":null,"name":null,"precedence":0,"observed_teamim":[]},"phrase_role":"JOIN","phrase_path":["w_5","n_5_6_join","n_5_8_split","n_1_8_split"],"clause_id":"C2","subclause_id":"C2.1","phrase_version":"phrase_tree.v1"},{"ref_key":"Deuteronomy/24/6","word_index":6,"surface":"נֶ֖פֶשׁ","primary_accent":{"word_index":6,"class":"DISJUNCTIVE","codepoint":"U+0596","name":"tipcha","precedence":1,"observed_teamim":["U+0596"]},"phrase_role":"SPLIT","phrase_path":["w_6","n_5_6_join","n_5_8_split","n_1_8_split"],"clause_id":"C2","subclause_id":"C2.1","phrase_version":"phrase_tree.v1"},{"ref_key":"Deuteronomy/24/6","word_index":7,"surface":"ה֥וּא","primary_accent":{"word_index":7,"class":"CONJUNCTIVE","codepoint":"U+05A5","name":"merkha","precedence":1,"observed_teamim":["U+05A5"]},"phrase_role":"JOIN","phrase_path":["w_7","n_7_8_join","n_5_8_split","n_1_8_split"],"clause_id":"C2","subclause_id":"C2.2","phrase_version":"phrase_tree.v1"},{"ref_key":"Deuteronomy/24/6","word_index":8,"surface":"חֹבֵל","primary_accent":{"word_index":8,"class":"NONE","codepoint":null,"name":null,"precedence":0,"observed_teamim":[]},"phrase_role":"TAIL","phrase_path":["w_8","n_7_8_join","n_5_8_split","n_1_8_split"],"clause_id":"C2","subclause_id":"C2.2","phrase_version":"phrase_tree.v1"}]}
