{"schema_version":1,"chunk_kind":"word_trace_bundle_chunk","verse_ref_key":"Genesis/12/10","ref":{"book":"Genesis","chapter":12,"verse":10},"word_traces":[{"record_kind":"WORD_TRACE","trace_version":"1.1.0","semantics_version":"1.1.0","render_version":"1.1.0","ref":{"book":"Genesis","chapter":12,"verse":10,"token_index":1},"ref_key":"Genesis/12/10/1","surface":"וַיְהִי","token_ids":[179,282,143,280],"events":[{"kind":"HE.DECLARE","index":0,"tau":1,"source":"vm_event","payload":{"id":"ה:1:1","mode":"public","target":"י:1:1"}}],"skeleton":["HE.DECLARE"],"flow":"ה declare(public)","mode":"WORD","canonical_hash":"881e3a3a60433ed2b78e2aeb38359c50215fc0696fd92e920cee49440d83ec5a"},{"record_kind":"WORD_TRACE","trace_version":"1.1.0","semantics_version":"1.1.0","render_version":"1.1.0","ref":{"book":"Genesis","chapter":12,"verse":10,"token_index":2},"ref_key":"Genesis/12/10/2","surface":"רָעָב","token_ids":[650,524,30],"events":[{"kind":"RESH.BOUNDARY_CLOSE","index":0,"tau":1,"source":"vm_event","payload":{"anchor":0,"id":"ר:1:1","inside":"Ω","outside":"Ω"}}],"skeleton":["RESH.BOUNDARY_CLOSE"],"flow":"ר boundary close","mode":"WORD","canonical_hash":"3bf355fbe56de83108d4cc1308683f52a9b5d7671dd75a3148acce4ef9c23d1e"},{"record_kind":"WORD_TRACE","trace_version":"1.1.0","semantics_version":"1.1.0","render_version":"1.1.0","ref":{"book":"Genesis","chapter":12,"verse":10,"token_index":3},"ref_key":"Genesis/12/10/3","surface":"בָּאָרֶץ","token_ids":[52,20,646,569],"events":[{"kind":"ALEPH.ALIAS","index":0,"tau":1,"source":"vm_event","payload":{"id":"א:1:1","left":"Ω","right":"ב:1:2"}},{"kind":"RESH.BOUNDARY_CLOSE","index":1,"tau":1,"source":"vm_event","payload":{"anchor":0,"id":"ר:1:1","inside":"ב:1:2","outside":"Ω"}},{"kind":"FINAL_TSADI.ALIGN_FINAL","index":2,"tau":1,"source":"vm_event","payload":{"exemplar":"ב:1:2","focus":"ר:1:1","id":"ץ:1:1"}}],"skeleton":["ALEPH.ALIAS","RESH.BOUNDARY_CLOSE","FINAL_TSADI.ALIGN_FINAL"],"flow":"א alias ⇢ ר boundary close ⇢ ץ final align","mode":"WORD","canonical_hash":"43ac19f247ec63390e35adcad282adae476ce9263d962b03d1f834cba3e7f8ce"},{"record_kind":"WORD_TRACE","trace_version":"1.1.0","semantics_version":"1.1.0","render_version":"1.1.0","ref":{"book":"Genesis","chapter":12,"verse":10,"token_index":4},"ref_key":"Genesis/12/10/4","surface":"וַיֵּרֶד","token_ids":[179,291,646,101],"events":[{"kind":"RESH.BOUNDARY_CLOSE","index":0,"tau":1,"source":"vm_event","payload":{"anchor":0,"id":"ר:1:1","inside":"י:1:1","outside":"Ω"}},{"kind":"DALET.BOUNDARY_CLOSE","index":1,"tau":1,"source":"vm_event","payload":{"id":"ד:1:1","inside":"ר:1:1","outside":"Ω"}}],"skeleton":["RESH.BOUNDARY_CLOSE","DALET.BOUNDARY_CLOSE"],"flow":"ר boundary close ⇢ ד boundary close","mode":"WORD","canonical_hash":"7086a3095d01dcc263e16c18a65419cd3a592a72c22825db7a3dfaa240baf598"},{"record_kind":"WORD_TRACE","trace_version":"1.1.0","semantics_version":"1.1.0","render_version":"1.1.0","ref":{"book":"Genesis","chapter":12,"verse":10,"token_index":5},"ref_key":"Genesis/12/10/5","surface":"אַבְרָם","token_ids":[17,31,650,400],"events":[{"kind":"ALEPH.ALIAS","index":0,"tau":1,"source":"vm_event","payload":{"id":"א:1:2","left":"Ω","right":"א:1:1"}},{"kind":"RESH.BOUNDARY_CLOSE","index":1,"tau":1,"source":"vm_event","payload":{"anchor":0,"id":"ר:1:1","inside":"ב:1:1","outside":"Ω"}},{"kind":"FINAL_MEM.CLOSE","index":2,"tau":1,"source":"derived_obligation","payload":{"action":"close","mode":"synthetic","obligation_kind":"MEM_ZONE"}}],"skeleton":["ALEPH.ALIAS","RESH.BOUNDARY_CLOSE","FINAL_MEM.CLOSE"],"flow":"א alias ⇢ ר boundary close ⇢ ם close mem-zone","mode":"WORD","canonical_hash":"49478a5c2aa995b211a1eadf5cb6d5075761d2e8cef38fa31ced6e317d23e740"},{"record_kind":"WORD_TRACE","trace_version":"1.1.0","semantics_version":"1.1.0","render_version":"1.1.0","ref":{"book":"Genesis","chapter":12,"verse":10,"token_index":6},"ref_key":"Genesis/12/10/6","surface":"מִצְרַיְמָה","token_ids":[406,572,648,282,422,136],"events":[{"kind":"MEM.OPEN","index":0,"tau":1,"source":"derived_obligation","payload":{"action":"open","obligation_kind":"MEM_ZONE"}},{"kind":"TSADI.ALIGN","index":1,"tau":1,"source":"vm_event","payload":{"exemplar":"⊥","focus":"Ω","id":"צ:1:1"}},{"kind":"RESH.BOUNDARY_CLOSE","index":2,"tau":1,"source":"vm_event","payload":{"anchor":0,"id":"ר:1:1","inside":"צ:1:1","outside":"Ω"}},{"kind":"MEM.OPEN","index":3,"tau":1,"source":"derived_obligation","payload":{"action":"open","obligation_kind":"MEM_ZONE"}},{"kind":"HE.DECLARE_BREATH","index":4,"tau":1,"source":"vm_event","payload":{"target":"י:1:1"}},{"kind":"SPACE.MEM_AUTO_CLOSE","index":5,"tau":2,"source":"derived_boundary","payload":{"action":"auto_close","count":1,"obligation_kind":"MEM_ZONE"}},{"kind":"SPACE.MEM_AUTO_CLOSE","index":6,"tau":2,"source":"derived_boundary","payload":{"action":"auto_close","count":1,"obligation_kind":"MEM_ZONE"}}],"skeleton":["MEM.OPEN","TSADI.ALIGN","RESH.BOUNDARY_CLOSE","MEM.OPEN","HE.DECLARE_BREATH","SPACE.MEM_AUTO_CLOSE"],"flow":"מ open mem-zone ⇢ צ normalize-to-exemplar ⇢ ר boundary close ⇢ מ open mem-zone ⇢ ה breath tail ⇢ □ mem auto-close","mode":"WORD","canonical_hash":"114c79ab111cf90e8bab810805190b5d9594cdcb04274abce2ac98d3563e2ef0"},{"record_kind":"WORD_TRACE","trace_version":"1.1.0","semantics_version":"1.1.0","render_version":"1.1.0","ref":{"book":"Genesis","chapter":12,"verse":10,"token_index":7},"ref_key":"Genesis/12/10/7","surface":"לָגוּר","token_ids":[385,68,193,639],"events":[{"kind":"LAMED.ENDPOINT","index":0,"tau":1,"source":"vm_event","payload":{"boundaryId":"ל:1:1","domain":"Ω","endpoint":"⊥","id":"ל:1:2"}},{"kind":"GIMEL.BESTOW","index":1,"tau":1,"source":"vm_event","payload":{"from":"ל:1:2","payload":"⊥","to":"ל:1:2"}},{"kind":"RESH.BOUNDARY_CLOSE","index":2,"tau":1,"source":"vm_event","payload":{"anchor":0,"id":"ר:1:1","inside":"ו:1:1","outside":"ו:1:2"}}],"skeleton":["LAMED.ENDPOINT","GIMEL.BESTOW","RESH.BOUNDARY_CLOSE"],"flow":"ל endpoint bind ⇢ ג bestowal ⇢ ר boundary close","mode":"WORD","canonical_hash":"4efad02e92ff09c3886c6b8c4f4b1b76e008874c15bfcd54d2a803b0e6e1fbad"},{"record_kind":"WORD_TRACE","trace_version":"1.1.0","semantics_version":"1.1.0","render_version":"1.1.0","ref":{"book":"Genesis","chapter":12,"verse":10,"token_index":8},"ref_key":"Genesis/12/10/8","surface":"שָׁם","token_ids":[702,400],"events":[{"kind":"SHIN.FORK","index":0,"tau":1,"source":"vm_event","payload":{"active":"right","focus":"Ω","id":"ש:1:4","left":"ש:1:2","right":"ש:1:3","spine":"ש:1:1"}},{"kind":"FINAL_MEM.CLOSE","index":1,"tau":1,"source":"derived_obligation","payload":{"action":"close","mode":"synthetic","obligation_kind":"MEM_ZONE"}}],"skeleton":["SHIN.FORK","FINAL_MEM.CLOSE"],"flow":"ש fork route ⇢ ם close mem-zone","mode":"WORD","canonical_hash":"d578a1318d601166c42935da63d1d629c9465498f78731ec88ae43d238c10730"},{"record_kind":"WORD_TRACE","trace_version":"1.1.0","semantics_version":"1.1.0","render_version":"1.1.0","ref":{"book":"Genesis","chapter":12,"verse":10,"token_index":9},"ref_key":"Genesis/12/10/9","surface":"כִּי","token_ids":[331,280],"events":[],"skeleton":[],"flow":"(no semantic events)","mode":"WORD","canonical_hash":"c422a5b953555dc82765db1b8ace5c8fed2ad8f3d120b955e9b0ecf6cb9bcc69"},{"record_kind":"WORD_TRACE","trace_version":"1.1.0","semantics_version":"1.1.0","render_version":"1.1.0","ref":{"book":"Genesis","chapter":12,"verse":10,"token_index":10},"ref_key":"Genesis/12/10/10","surface":"כָבֵד","token_ids":[346,39,101],"events":[{"kind":"DALET.BOUNDARY_CLOSE","index":0,"tau":1,"source":"vm_event","payload":{"id":"ד:1:1","inside":"ב:1:1","outside":"Ω"}}],"skeleton":["DALET.BOUNDARY_CLOSE"],"flow":"ד boundary close","mode":"WORD","canonical_hash":"cce5cb8c7595010d18e6708f35e4d02031e5cc851aa2931f23de7b5737a3e814"},{"record_kind":"WORD_TRACE","trace_version":"1.1.0","semantics_version":"1.1.0","render_version":"1.1.0","ref":{"book":"Genesis","chapter":12,"verse":10,"token_index":11},"ref_key":"Genesis/12/10/11","surface":"הָרָעָב","token_ids":[152,650,524,30],"events":[{"kind":"HE.DECLARE","index":0,"tau":1,"source":"vm_event","payload":{"id":"ה:1:1","mode":"public","target":"Ω"}},{"kind":"RESH.BOUNDARY_CLOSE","index":1,"tau":1,"source":"vm_event","payload":{"anchor":0,"id":"ר:1:1","inside":"ה:1:1","outside":"Ω"}}],"skeleton":["HE.DECLARE","RESH.BOUNDARY_CLOSE"],"flow":"ה declare(public) ⇢ ר boundary close","mode":"WORD","canonical_hash":"62447a1ccd30543185c3b46112c77a8847683393219f2a15ec8e5700ab3c5a11"},{"record_kind":"WORD_TRACE","trace_version":"1.1.0","semantics_version":"1.1.0","render_version":"1.1.0","ref":{"book":"Genesis","chapter":12,"verse":10,"token_index":12},"ref_key":"Genesis/12/10/12","surface":"בָּאָרֶץ","token_ids":[52,20,646,569],"events":[{"kind":"ALEPH.ALIAS","index":0,"tau":1,"source":"vm_event","payload":{"id":"א:1:1","left":"Ω","right":"ב:1:2"}},{"kind":"RESH.BOUNDARY_CLOSE","index":1,"tau":1,"source":"vm_event","payload":{"anchor":0,"id":"ר:1:1","inside":"ב:1:2","outside":"Ω"}},{"kind":"FINAL_TSADI.ALIGN_FINAL","index":2,"tau":1,"source":"vm_event","payload":{"exemplar":"ב:1:2","focus":"ר:1:1","id":"ץ:1:1"}}],"skeleton":["ALEPH.ALIAS","RESH.BOUNDARY_CLOSE","FINAL_TSADI.ALIGN_FINAL"],"flow":"א alias ⇢ ר boundary close ⇢ ץ final align","mode":"WORD","canonical_hash":"1d2484a45d462522b34c20fcdaa3674af0a39a7adf08762685cf19751a98d30e"}],"word_phrase_roles":[{"ref_key":"Genesis/12/10","word_index":1,"surface":"וַיְהִ֥י","primary_accent":{"word_index":1,"class":"CONJUNCTIVE","codepoint":"U+05A5","name":"merkha","precedence":1,"observed_teamim":["U+05A5"]},"phrase_role":"HEAD","phrase_path":["w_1","n_1_2_join","n_1_3_split","n_1_12_split"],"clause_id":"C1","subclause_id":"C1.1","phrase_version":"phrase_tree.v1"},{"ref_key":"Genesis/12/10","word_index":2,"surface":"רָעָ֖ב","primary_accent":{"word_index":2,"class":"DISJUNCTIVE","codepoint":"U+0596","name":"tipcha","precedence":1,"observed_teamim":["U+0596"]},"phrase_role":"SPLIT","phrase_path":["w_2","n_1_2_join","n_1_3_split","n_1_12_split"],"clause_id":"C1","subclause_id":"C1.1","phrase_version":"phrase_tree.v1"},{"ref_key":"Genesis/12/10","word_index":3,"surface":"בָּאָ֑רֶץ","primary_accent":{"word_index":3,"class":"DISJUNCTIVE","codepoint":"U+0591","name":"etnahta","precedence":2,"observed_teamim":["U+0591"]},"phrase_role":"SPLIT","phrase_path":["w_3","n_1_3_split","n_1_12_split"],"clause_id":"C1","subclause_id":"C1.2","phrase_version":"phrase_tree.v1"},{"ref_key":"Genesis/12/10","word_index":4,"surface":"וַיֵּ֨רֶד","primary_accent":{"word_index":4,"class":"CONJUNCTIVE","codepoint":"U+05A8","name":"qadma","precedence":1,"observed_teamim":["U+05A8"]},"phrase_role":"JOIN","phrase_path":["w_4","n_4_5_join","n_4_6_join","n_4_8_split","n_4_12_split","n_1_12_split"],"clause_id":"C2","subclause_id":"C2.1.1","phrase_version":"phrase_tree.v1"},{"ref_key":"Genesis/12/10","word_index":5,"surface":"אַבְרָ֤ם","primary_accent":{"word_index":5,"class":"CONJUNCTIVE","codepoint":"U+05A4","name":"mahpakh","precedence":1,"observed_teamim":["U+05A4"]},"phrase_role":"JOIN","phrase_path":["w_5","n_4_5_join","n_4_6_join","n_4_8_split","n_4_12_split","n_1_12_split"],"clause_id":"C2","subclause_id":"C2.1.1","phrase_version":"phrase_tree.v1"},{"ref_key":"Genesis/12/10","word_index":6,"surface":"מִצְרַ֙יְמָה֙","primary_accent":{"word_index":6,"class":"DISJUNCTIVE","codepoint":"U+0599","name":"pashta","precedence":2,"observed_teamim":["U+0599"]},"phrase_role":"SPLIT","phrase_path":["w_6","n_4_6_join","n_4_8_split","n_4_12_split","n_1_12_split"],"clause_id":"C2","subclause_id":"C2.1.1","phrase_version":"phrase_tree.v1"},{"ref_key":"Genesis/12/10","word_index":7,"surface":"לָג֣וּר","primary_accent":{"word_index":7,"class":"CONJUNCTIVE","codepoint":"U+05A3","name":"munach","precedence":1,"observed_teamim":["U+05A3"]},"phrase_role":"JOIN","phrase_path":["w_7","n_7_8_join","n_4_8_split","n_4_12_split","n_1_12_split"],"clause_id":"C2","subclause_id":"C2.1.2","phrase_version":"phrase_tree.v1"},{"ref_key":"Genesis/12/10","word_index":8,"surface":"שָׁ֔ם","primary_accent":{"word_index":8,"class":"DISJUNCTIVE","codepoint":"U+0594","name":"zaqef_qatan","precedence":2,"observed_teamim":["U+0594"]},"phrase_role":"SPLIT","phrase_path":["w_8","n_7_8_join","n_4_8_split","n_4_12_split","n_1_12_split"],"clause_id":"C2","subclause_id":"C2.1.2","phrase_version":"phrase_tree.v1"},{"ref_key":"Genesis/12/10","word_index":9,"surface":"כִּי","primary_accent":{"word_index":9,"class":"NONE","codepoint":null,"name":null,"precedence":0,"observed_teamim":[]},"phrase_role":"JOIN","phrase_path":["w_9","n_9_10_join","n_9_11_join","n_9_12_split","n_4_12_split","n_1_12_split"],"clause_id":"C2","subclause_id":"C2.2.1","phrase_version":"phrase_tree.v1"},{"ref_key":"Genesis/12/10","word_index":10,"surface":"כָבֵ֥ד","primary_accent":{"word_index":10,"class":"CONJUNCTIVE","codepoint":"U+05A5","name":"merkha","precedence":1,"observed_teamim":["U+05A5"]},"phrase_role":"JOIN","phrase_path":["w_10","n_9_10_join","n_9_11_join","n_9_12_split","n_4_12_split","n_1_12_split"],"clause_id":"C2","subclause_id":"C2.2.1","phrase_version":"phrase_tree.v1"},{"ref_key":"Genesis/12/10","word_index":11,"surface":"הָרָעָ֖ב","primary_accent":{"word_index":11,"class":"DISJUNCTIVE","codepoint":"U+0596","name":"tipcha","precedence":1,"observed_teamim":["U+0596"]},"phrase_role":"SPLIT","phrase_path":["w_11","n_9_11_join","n_9_12_split","n_4_12_split","n_1_12_split"],"clause_id":"C2","subclause_id":"C2.2.1","phrase_version":"phrase_tree.v1"},{"ref_key":"Genesis/12/10","word_index":12,"surface":"בָּאָרֶץ","primary_accent":{"word_index":12,"class":"NONE","codepoint":null,"name":null,"precedence":0,"observed_teamim":[]},"phrase_role":"TAIL","phrase_path":["w_12","n_9_12_split","n_4_12_split","n_1_12_split"],"clause_id":"C2","subclause_id":"C2.2.2","phrase_version":"phrase_tree.v1"}]}
