{"schema_version":1,"chunk_kind":"word_trace_bundle_chunk","verse_ref_key":"Leviticus/15/14","ref":{"book":"Leviticus","chapter":15,"verse":14},"word_traces":[{"record_kind":"WORD_TRACE","trace_version":"1.1.0","semantics_version":"1.1.0","render_version":"1.1.0","ref":{"book":"Leviticus","chapter":15,"verse":14,"token_index":1},"ref_key":"Leviticus/15/14/1","surface":"וּבַיּוֹם","token_ids":[193,47,312,187,400],"events":[{"kind":"FINAL_MEM.CLOSE","index":0,"tau":1,"source":"derived_obligation","payload":{"action":"close","mode":"synthetic","obligation_kind":"MEM_ZONE"}}],"skeleton":["FINAL_MEM.CLOSE"],"flow":"ם close mem-zone","mode":"WORD","canonical_hash":"a80b4c4d1be1e615f3c467c68ac10d19f72c9106127a5413d4510aa5e253d666"},{"record_kind":"WORD_TRACE","trace_version":"1.1.0","semantics_version":"1.1.0","render_version":"1.1.0","ref":{"book":"Leviticus","chapter":15,"verse":14,"token_index":2},"ref_key":"Leviticus/15/14/2","surface":"הַשְּׁמִינִי","token_ids":[149,661,406,280,446,280],"events":[{"kind":"HE.DECLARE","index":0,"tau":1,"source":"vm_event","payload":{"id":"ה:1:1","mode":"public","target":"Ω"}},{"kind":"SHIN.FORK","index":1,"tau":1,"source":"vm_event","payload":{"active":"right","focus":"ה:1:1","id":"ש:1:4","left":"ש:1:2","right":"ש:1:3","spine":"ש:1:1"}},{"kind":"MEM.OPEN","index":2,"tau":1,"source":"derived_obligation","payload":{"action":"open","obligation_kind":"MEM_ZONE"}},{"kind":"NUN.SUPPORT_DEBT","index":3,"tau":1,"source":"derived_obligation","payload":{"action":"open","obligation_kind":"SUPPORT"}},{"kind":"SPACE.SUPPORT_DISCHARGE","index":4,"tau":2,"source":"vm_event","payload":{"child":"נ:1:1","parent":"י:1:1"}},{"kind":"SPACE.MEM_AUTO_CLOSE","index":5,"tau":2,"source":"derived_boundary","payload":{"action":"auto_close","count":1,"obligation_kind":"MEM_ZONE"}}],"skeleton":["HE.DECLARE","SHIN.FORK","MEM.OPEN","NUN.SUPPORT_DEBT","SPACE.SUPPORT_DISCHARGE","SPACE.MEM_AUTO_CLOSE"],"flow":"ה declare(public) ⇢ ש fork route ⇢ מ open mem-zone ⇢ נ support debt ⇢ □ boundary support discharge ⇢ □ mem auto-close","mode":"WORD","canonical_hash":"03ae193af76a4fb41cc6934e852d5b7018a01b8b8a2b692b74cb6278199d0f83"},{"record_kind":"WORD_TRACE","trace_version":"1.1.0","semantics_version":"1.1.0","render_version":"1.1.0","ref":{"book":"Leviticus","chapter":15,"verse":14,"token_index":3},"ref_key":"Leviticus/15/14/3","surface":"יִקַּח","token_ids":[285,620,228],"events":[{"kind":"QOF.APPROX","index":0,"tau":1,"source":"vm_event","payload":{"id":"ק:1:1","left":"י:1:1","right":"⊥"}},{"kind":"HET.COMPARTMENT","index":1,"tau":1,"source":"vm_event","payload":{"boundaryId":"ח:1:1","id":"ח:1:2","inside":"ק:1:1","outside":"Ω"}}],"skeleton":["QOF.APPROX","HET.COMPARTMENT"],"flow":"ק approximate ⇢ ח compartment","mode":"WORD","canonical_hash":"b6e3cf1920785ad40d193aa541a1f6399fcb5e1d90c293bcef2cf565ab93ac6e"},{"record_kind":"WORD_TRACE","trace_version":"1.1.0","semantics_version":"1.1.0","render_version":"1.1.0","ref":{"book":"Leviticus","chapter":15,"verse":14,"token_index":4},"ref_key":"Leviticus/15/14/4","surface":"לוֹ","token_ids":[364,187],"events":[{"kind":"LAMED.ENDPOINT","index":0,"tau":1,"source":"vm_event","payload":{"boundaryId":"ל:1:1","domain":"Ω","endpoint":"⊥","id":"ל:1:2"}}],"skeleton":["LAMED.ENDPOINT"],"flow":"ל endpoint bind","mode":"WORD","canonical_hash":"965e15f4aea08d2a932adbe2142fdbbe7db97253666b38236cc663a829220a3f"},{"record_kind":"WORD_TRACE","trace_version":"1.1.0","semantics_version":"1.1.0","render_version":"1.1.0","ref":{"book":"Leviticus","chapter":15,"verse":14,"token_index":5},"ref_key":"Leviticus/15/14/5","surface":"שְׁתֵּי","token_ids":[664,736,280],"events":[{"kind":"SHIN.FORK","index":0,"tau":1,"source":"vm_event","payload":{"active":"right","focus":"Ω","id":"ש:1:4","left":"ש:1:2","right":"ש:1:3","spine":"ש:1:1"}},{"kind":"TAV.FINALIZE","index":1,"tau":1,"source":"vm_event","payload":{"boundaryId":"ת:1:1","id":"ת:1:2","outside":"Ω","residueId":"ת:1:3","target":"ש:1:4"}}],"skeleton":["SHIN.FORK","TAV.FINALIZE"],"flow":"ש fork route ⇢ ת finalize+stamp","mode":"WORD","canonical_hash":"ccb1564530849347b567fadc39adac019b7dc7ad518b2bc47f13eacd96a0ae7e"},{"record_kind":"WORD_TRACE","trace_version":"1.1.0","semantics_version":"1.1.0","render_version":"1.1.0","ref":{"book":"Leviticus","chapter":15,"verse":14,"token_index":6},"ref_key":"Leviticus/15/14/6","surface":"תֹרִים","token_ids":[751,642,280,400],"events":[{"kind":"TAV.FINALIZE","index":0,"tau":1,"source":"vm_event","payload":{"boundaryId":"ת:1:1","id":"ת:1:2","outside":"Ω","residueId":"ת:1:3","target":"Ω"}},{"kind":"RESH.BOUNDARY_CLOSE","index":1,"tau":1,"source":"vm_event","payload":{"anchor":0,"id":"ר:1:1","inside":"ת:1:3","outside":"ת:1:2"}},{"kind":"FINAL_MEM.CLOSE","index":2,"tau":1,"source":"derived_obligation","payload":{"action":"close","mode":"synthetic","obligation_kind":"MEM_ZONE"}}],"skeleton":["TAV.FINALIZE","RESH.BOUNDARY_CLOSE","FINAL_MEM.CLOSE"],"flow":"ת finalize+stamp ⇢ ר boundary close ⇢ ם close mem-zone","mode":"WORD","canonical_hash":"356c8e571e777e43f6152c7e7b2346e958302ead550f11088d8a1c019c59cfea"},{"record_kind":"WORD_TRACE","trace_version":"1.1.0","semantics_version":"1.1.0","render_version":"1.1.0","ref":{"book":"Leviticus","chapter":15,"verse":14,"token_index":7},"ref_key":"Leviticus/15/14/7","surface":"אוֹ","token_ids":[1,187],"events":[{"kind":"ALEPH.ALIAS","index":0,"tau":1,"source":"vm_event","payload":{"id":"א:1:2","left":"Ω","right":"א:1:1"}}],"skeleton":["ALEPH.ALIAS"],"flow":"א alias","mode":"WORD","canonical_hash":"f5eb247cebd511218f961dd714edf09232d606453e5dcd91ed103589b74c1c29"},{"record_kind":"WORD_TRACE","trace_version":"1.1.0","semantics_version":"1.1.0","render_version":"1.1.0","ref":{"book":"Leviticus","chapter":15,"verse":14,"token_index":8},"ref_key":"Leviticus/15/14/8","surface":"שְׁנֵי","token_ids":[664,450,280],"events":[{"kind":"SHIN.FORK","index":0,"tau":1,"source":"vm_event","payload":{"active":"right","focus":"Ω","id":"ש:1:4","left":"ש:1:2","right":"ש:1:3","spine":"ש:1:1"}},{"kind":"NUN.SUPPORT_DEBT","index":1,"tau":1,"source":"derived_obligation","payload":{"action":"open","obligation_kind":"SUPPORT"}},{"kind":"SPACE.SUPPORT_DISCHARGE","index":2,"tau":2,"source":"vm_event","payload":{"child":"נ:1:1","parent":"ש:1:4"}}],"skeleton":["SHIN.FORK","NUN.SUPPORT_DEBT","SPACE.SUPPORT_DISCHARGE"],"flow":"ש fork route ⇢ נ support debt ⇢ □ boundary support discharge","mode":"WORD","canonical_hash":"68a3352b2baa80efc153fbd61c8323fcd9c5fc6c3934ef4b0db9099fa4f8d958"},{"record_kind":"WORD_TRACE","trace_version":"1.1.0","semantics_version":"1.1.0","render_version":"1.1.0","ref":{"book":"Leviticus","chapter":15,"verse":14,"token_index":9},"ref_key":"Leviticus/15/14/9","surface":"בְּנֵי","token_ids":[32,450,280],"events":[{"kind":"NUN.SUPPORT_DEBT","index":0,"tau":1,"source":"derived_obligation","payload":{"action":"open","obligation_kind":"SUPPORT"}},{"kind":"SPACE.SUPPORT_DISCHARGE","index":1,"tau":2,"source":"vm_event","payload":{"child":"נ:1:1","parent":"ב:1:2"}}],"skeleton":["NUN.SUPPORT_DEBT","SPACE.SUPPORT_DISCHARGE"],"flow":"נ support debt ⇢ □ boundary support discharge","mode":"WORD","canonical_hash":"642f0ce555a04ce58d0817e118a2278b2c2e7b5df7ab57a394227bf3c37e082b"},{"record_kind":"WORD_TRACE","trace_version":"1.1.0","semantics_version":"1.1.0","render_version":"1.1.0","ref":{"book":"Leviticus","chapter":15,"verse":14,"token_index":10},"ref_key":"Leviticus/15/14/10","surface":"יוֹנָה","token_ids":[280,187,463,136],"events":[{"kind":"NUN.SUPPORT_DEBT","index":0,"tau":1,"source":"derived_obligation","payload":{"action":"open","obligation_kind":"SUPPORT"}},{"kind":"HE.DECLARE_BREATH","index":1,"tau":1,"source":"vm_event","payload":{"target":"נ:1:1"}},{"kind":"SPACE.SUPPORT_DISCHARGE","index":2,"tau":2,"source":"vm_event","payload":{"child":"נ:1:1","parent":"ו:1:1"}}],"skeleton":["NUN.SUPPORT_DEBT","HE.DECLARE_BREATH","SPACE.SUPPORT_DISCHARGE"],"flow":"נ support debt ⇢ ה breath tail ⇢ □ boundary support discharge","mode":"WORD","canonical_hash":"67eda840ebb7c928b47bf2ecaa219c75e1dbcee4c8e714b5df668e10ca0f6c10"},{"record_kind":"WORD_TRACE","trace_version":"1.1.0","semantics_version":"1.1.0","render_version":"1.1.0","ref":{"book":"Leviticus","chapter":15,"verse":14,"token_index":11},"ref_key":"Leviticus/15/14/11","surface":"וּבָא","token_ids":[193,51,1],"events":[{"kind":"ALEPH.ALIAS","index":0,"tau":1,"source":"vm_event","payload":{"id":"א:1:1","left":"Ω","right":"ב:1:1"}}],"skeleton":["ALEPH.ALIAS"],"flow":"א alias","mode":"WORD","canonical_hash":"a431dcd4284e94ad484405333d8dce45264153778a703c56c032f5959999d641"},{"record_kind":"WORD_TRACE","trace_version":"1.1.0","semantics_version":"1.1.0","render_version":"1.1.0","ref":{"book":"Leviticus","chapter":15,"verse":14,"token_index":12},"ref_key":"Leviticus/15/14/12","surface":"לִפְנֵי","token_ids":[369,534,450,280],"events":[{"kind":"LAMED.ENDPOINT","index":0,"tau":1,"source":"vm_event","payload":{"boundaryId":"ל:1:1","domain":"Ω","endpoint":"⊥","id":"ל:1:2"}},{"kind":"PE.UTTER","index":1,"tau":1,"source":"vm_event","payload":{"id":"פ:1:1","payload":"ל:1:2","source":"ל:1:2","target":"⊥"}},{"kind":"NUN.SUPPORT_DEBT","index":2,"tau":1,"source":"derived_obligation","payload":{"action":"open","obligation_kind":"SUPPORT"}},{"kind":"SPACE.SUPPORT_DISCHARGE","index":3,"tau":2,"source":"vm_event","payload":{"child":"נ:1:1","parent":"פ:1:1"}}],"skeleton":["LAMED.ENDPOINT","PE.UTTER","NUN.SUPPORT_DEBT","SPACE.SUPPORT_DISCHARGE"],"flow":"ל endpoint bind ⇢ פ utterance ⇢ נ support debt ⇢ □ boundary support discharge","mode":"WORD","canonical_hash":"2f8b6828a045973ca796be523b9ac5290f81a5e29c25f9a5a3e636811db40de5"},{"record_kind":"WORD_TRACE","trace_version":"1.1.0","semantics_version":"1.1.0","render_version":"1.1.0","ref":{"book":"Leviticus","chapter":15,"verse":14,"token_index":13},"ref_key":"Leviticus/15/14/13","surface":"יְהֹוָה","token_ids":[282,154,183,136],"events":[{"kind":"HE.DECLARE","index":0,"tau":1,"source":"vm_event","payload":{"id":"ה:1:1","mode":"public","target":"י:1:1"}},{"kind":"HE.DECLARE_BREATH","index":1,"tau":1,"source":"vm_event","payload":{"target":"ו:1:1"}}],"skeleton":["HE.DECLARE","HE.DECLARE_BREATH"],"flow":"ה declare(public) ⇢ ה breath tail","mode":"WORD","canonical_hash":"3ec3405b056f094e6abdf1a122e2daca662b782845b54bbd8825b44d526e00d2"},{"record_kind":"WORD_TRACE","trace_version":"1.1.0","semantics_version":"1.1.0","render_version":"1.1.0","ref":{"book":"Leviticus","chapter":15,"verse":14,"token_index":14},"ref_key":"Leviticus/15/14/14","surface":"אֶל","token_ids":[14,364],"events":[{"kind":"ALEPH.ALIAS","index":0,"tau":1,"source":"vm_event","payload":{"id":"א:1:2","left":"Ω","right":"א:1:1"}},{"kind":"LAMED.ENDPOINT","index":1,"tau":1,"source":"vm_event","payload":{"boundaryId":"ל:1:1","domain":"⊥","endpoint":"א:1:1","id":"ל:1:2"}}],"skeleton":["ALEPH.ALIAS","LAMED.ENDPOINT"],"flow":"א alias ⇢ ל endpoint bind","mode":"WORD","canonical_hash":"0fecaa886ea38ed9c73ea1b0cc0fe4cd72dac76783e43db2f95303aaa5cf911d"},{"record_kind":"WORD_TRACE","trace_version":"1.1.0","semantics_version":"1.1.0","render_version":"1.1.0","ref":{"book":"Leviticus","chapter":15,"verse":14,"token_index":15},"ref_key":"Leviticus/15/14/15","surface":"פֶּתַח","token_ids":[546,743,228],"events":[{"kind":"PE.UTTER","index":0,"tau":1,"source":"vm_event","payload":{"id":"פ:1:1","payload":"Ω","source":"⊥","target":"Ω"}},{"kind":"TAV.FINALIZE","index":1,"tau":1,"source":"vm_event","payload":{"boundaryId":"ת:1:1","id":"ת:1:2","outside":"Ω","residueId":"ת:1:3","target":"פ:1:1"}},{"kind":"HET.COMPARTMENT","index":2,"tau":1,"source":"vm_event","payload":{"boundaryId":"ח:1:1","id":"ח:1:2","inside":"ת:1:3","outside":"ת:1:2"}}],"skeleton":["PE.UTTER","TAV.FINALIZE","HET.COMPARTMENT"],"flow":"פ utterance ⇢ ת finalize+stamp ⇢ ח compartment","mode":"WORD","canonical_hash":"b7981821b3eebf23bf9e7f8fcc32d729f86b81818c1e51c4951bb68dcd761401"},{"record_kind":"WORD_TRACE","trace_version":"1.1.0","semantics_version":"1.1.0","render_version":"1.1.0","ref":{"book":"Leviticus","chapter":15,"verse":14,"token_index":16},"ref_key":"Leviticus/15/14/16","surface":"אֹהֶל","token_ids":[22,147,364],"events":[{"kind":"ALEPH.ALIAS","index":0,"tau":1,"source":"vm_event","payload":{"id":"א:1:2","left":"Ω","right":"א:1:1"}},{"kind":"HE.DECLARE","index":1,"tau":1,"source":"vm_event","payload":{"id":"ה:1:1","mode":"public","target":"א:1:1"}},{"kind":"LAMED.ENDPOINT","index":2,"tau":1,"source":"vm_event","payload":{"boundaryId":"ל:1:1","domain":"א:1:1","endpoint":"ה:1:1","id":"ל:1:2"}}],"skeleton":["ALEPH.ALIAS","HE.DECLARE","LAMED.ENDPOINT"],"flow":"א alias ⇢ ה declare(public) ⇢ ל endpoint bind","mode":"WORD","canonical_hash":"046912a0fa525e57ab35cad3dffac07829f1b316f3e5604c37d7e0a9a3cad206"},{"record_kind":"WORD_TRACE","trace_version":"1.1.0","semantics_version":"1.1.0","render_version":"1.1.0","ref":{"book":"Leviticus","chapter":15,"verse":14,"token_index":17},"ref_key":"Leviticus/15/14/17","surface":"מוֹעֵד","token_ids":[401,187,517,101],"events":[{"kind":"MEM.OPEN","index":0,"tau":1,"source":"derived_obligation","payload":{"action":"open","obligation_kind":"MEM_ZONE"}},{"kind":"DALET.BOUNDARY_CLOSE","index":1,"tau":1,"source":"vm_event","payload":{"id":"ד:1:1","inside":"ע:1:1","outside":"Ω"}},{"kind":"SPACE.MEM_AUTO_CLOSE","index":2,"tau":2,"source":"derived_boundary","payload":{"action":"auto_close","count":1,"obligation_kind":"MEM_ZONE"}}],"skeleton":["MEM.OPEN","DALET.BOUNDARY_CLOSE","SPACE.MEM_AUTO_CLOSE"],"flow":"מ open mem-zone ⇢ ד boundary close ⇢ □ mem auto-close","mode":"WORD","canonical_hash":"8a7ed9adf744dc4e15e94ebd4043196833132e5de15414081815ec1b571ee77f"},{"record_kind":"WORD_TRACE","trace_version":"1.1.0","semantics_version":"1.1.0","render_version":"1.1.0","ref":{"book":"Leviticus","chapter":15,"verse":14,"token_index":18},"ref_key":"Leviticus/15/14/18","surface":"וּנְתָנָם","token_ids":[193,444,747,463,400],"events":[{"kind":"NUN.SUPPORT_DEBT","index":0,"tau":1,"source":"derived_obligation","payload":{"action":"open","obligation_kind":"SUPPORT"}},{"kind":"TAV.FINALIZE","index":1,"tau":1,"source":"vm_event","payload":{"boundaryId":"ת:1:1","id":"ת:1:2","outside":"Ω","residueId":"ת:1:3","target":"נ:1:1"}},{"kind":"NUN.SUPPORT_DEBT","index":2,"tau":1,"source":"derived_obligation","payload":{"action":"open","obligation_kind":"SUPPORT"}},{"kind":"FINAL_MEM.CLOSE","index":3,"tau":1,"source":"derived_obligation","payload":{"action":"close","mode":"synthetic","obligation_kind":"MEM_ZONE"}},{"kind":"SPACE.SUPPORT_DISCHARGE","index":4,"tau":2,"source":"vm_event","payload":{"child":"נ:1:2","parent":"ת:1:3"}},{"kind":"SPACE.SUPPORT_DISCHARGE","index":5,"tau":2,"source":"vm_event","payload":{"child":"נ:1:1","parent":"ו:1:1"}}],"skeleton":["NUN.SUPPORT_DEBT","TAV.FINALIZE","NUN.SUPPORT_DEBT","FINAL_MEM.CLOSE","SPACE.SUPPORT_DISCHARGE"],"flow":"נ support debt ⇢ ת finalize+stamp ⇢ נ support debt ⇢ ם close mem-zone ⇢ □ boundary support discharge","mode":"WORD","canonical_hash":"bd39131ae987a3c054e17d94319690bfd151e9c051cd5ddac0930ae2c3af35be"},{"record_kind":"WORD_TRACE","trace_version":"1.1.0","semantics_version":"1.1.0","render_version":"1.1.0","ref":{"book":"Leviticus","chapter":15,"verse":14,"token_index":19},"ref_key":"Leviticus/15/14/19","surface":"אֶל","token_ids":[14,364],"events":[{"kind":"ALEPH.ALIAS","index":0,"tau":1,"source":"vm_event","payload":{"id":"א:1:2","left":"Ω","right":"א:1:1"}},{"kind":"LAMED.ENDPOINT","index":1,"tau":1,"source":"vm_event","payload":{"boundaryId":"ל:1:1","domain":"⊥","endpoint":"א:1:1","id":"ל:1:2"}}],"skeleton":["ALEPH.ALIAS","LAMED.ENDPOINT"],"flow":"א alias ⇢ ל endpoint bind","mode":"WORD","canonical_hash":"3b04c7416227d8e9730cfb5efb6d68e047a6e2ef80301f0783d3b420fcadd1d0"},{"record_kind":"WORD_TRACE","trace_version":"1.1.0","semantics_version":"1.1.0","render_version":"1.1.0","ref":{"book":"Leviticus","chapter":15,"verse":14,"token_index":20},"ref_key":"Leviticus/15/14/20","surface":"הַכֹּהֵן","token_ids":[149,351,145,439],"events":[{"kind":"HE.DECLARE","index":0,"tau":1,"source":"vm_event","payload":{"id":"ה:1:1","mode":"public","target":"Ω"}},{"kind":"HE.DECLARE","index":1,"tau":1,"source":"vm_event","payload":{"id":"ה:1:2","mode":"public","target":"כ:1:1"}},{"kind":"FINAL_NUN.SUPPORT_DEBT","index":2,"tau":1,"source":"derived_obligation","payload":{"action":"open","obligation_kind":"SUPPORT"}},{"kind":"FINAL_NUN.SUPPORT_DISCHARGE","index":3,"tau":1,"source":"derived_obligation","payload":{"action":"discharge","mode":"same_word","obligation_kind":"SUPPORT"}}],"skeleton":["HE.DECLARE","FINAL_NUN.SUPPORT_DEBT","FINAL_NUN.SUPPORT_DISCHARGE"],"flow":"ה declare(public) ⇢ ן support debt ⇢ ן same-word discharge","mode":"WORD","canonical_hash":"695a12ad4cbc21c1c2e09168e6b3f95c9af8a364a9699cc6af93740c66c66cdc"}],"word_phrase_roles":[{"ref_key":"Leviticus/15/14","word_index":1,"surface":"וּבַיּ֣וֹם","primary_accent":{"word_index":1,"class":"CONJUNCTIVE","codepoint":"U+05A3","name":"munach","precedence":1,"observed_teamim":["U+05A3"]},"phrase_role":"HEAD","phrase_path":["w_1","n_1_2_join","n_1_6_split","n_1_10_split","n_1_20_split"],"clause_id":"C1","subclause_id":"C1.1.1","phrase_version":"phrase_tree.v1"},{"ref_key":"Leviticus/15/14","word_index":2,"surface":"הַשְּׁמִינִ֗י","primary_accent":{"word_index":2,"class":"DISJUNCTIVE","codepoint":"U+0597","name":"revia","precedence":2,"observed_teamim":["U+0597"]},"phrase_role":"SPLIT","phrase_path":["w_2","n_1_2_join","n_1_6_split","n_1_10_split","n_1_20_split"],"clause_id":"C1","subclause_id":"C1.1.1","phrase_version":"phrase_tree.v1"},{"ref_key":"Leviticus/15/14","word_index":3,"surface":"יִקַּח","primary_accent":{"word_index":3,"class":"NONE","codepoint":null,"name":null,"precedence":0,"observed_teamim":[]},"phrase_role":"JOIN","phrase_path":["w_3","n_3_4_join","n_3_6_split","n_1_6_split","n_1_10_split","n_1_20_split"],"clause_id":"C1","subclause_id":"C1.1.2.1","phrase_version":"phrase_tree.v1"},{"ref_key":"Leviticus/15/14","word_index":4,"surface":"לוֹ֙","primary_accent":{"word_index":4,"class":"DISJUNCTIVE","codepoint":"U+0599","name":"pashta","precedence":2,"observed_teamim":["U+0599"]},"phrase_role":"SPLIT","phrase_path":["w_4","n_3_4_join","n_3_6_split","n_1_6_split","n_1_10_split","n_1_20_split"],"clause_id":"C1","subclause_id":"C1.1.2.1","phrase_version":"phrase_tree.v1"},{"ref_key":"Leviticus/15/14","word_index":5,"surface":"שְׁתֵּ֣י","primary_accent":{"word_index":5,"class":"CONJUNCTIVE","codepoint":"U+05A3","name":"munach","precedence":1,"observed_teamim":["U+05A3"]},"phrase_role":"JOIN","phrase_path":["w_5","n_5_6_join","n_3_6_split","n_1_6_split","n_1_10_split","n_1_20_split"],"clause_id":"C1","subclause_id":"C1.1.2.2","phrase_version":"phrase_tree.v1"},{"ref_key":"Leviticus/15/14","word_index":6,"surface":"תֹרִ֔ים","primary_accent":{"word_index":6,"class":"DISJUNCTIVE","codepoint":"U+0594","name":"zaqef_qatan","precedence":2,"observed_teamim":["U+0594"]},"phrase_role":"SPLIT","phrase_path":["w_6","n_5_6_join","n_3_6_split","n_1_6_split","n_1_10_split","n_1_20_split"],"clause_id":"C1","subclause_id":"C1.1.2.2","phrase_version":"phrase_tree.v1"},{"ref_key":"Leviticus/15/14","word_index":7,"surface":"א֥וֹ","primary_accent":{"word_index":7,"class":"CONJUNCTIVE","codepoint":"U+05A5","name":"merkha","precedence":1,"observed_teamim":["U+05A5"]},"phrase_role":"JOIN","phrase_path":["w_7","n_7_8_join","n_7_10_split","n_1_10_split","n_1_20_split"],"clause_id":"C1","subclause_id":"C1.2.1","phrase_version":"phrase_tree.v1"},{"ref_key":"Leviticus/15/14","word_index":8,"surface":"שְׁנֵ֖י","primary_accent":{"word_index":8,"class":"DISJUNCTIVE","codepoint":"U+0596","name":"tipcha","precedence":1,"observed_teamim":["U+0596"]},"phrase_role":"SPLIT","phrase_path":["w_8","n_7_8_join","n_7_10_split","n_1_10_split","n_1_20_split"],"clause_id":"C1","subclause_id":"C1.2.1","phrase_version":"phrase_tree.v1"},{"ref_key":"Leviticus/15/14","word_index":9,"surface":"בְּנֵ֣י","primary_accent":{"word_index":9,"class":"CONJUNCTIVE","codepoint":"U+05A3","name":"munach","precedence":1,"observed_teamim":["U+05A3"]},"phrase_role":"JOIN","phrase_path":["w_9","n_9_10_join","n_7_10_split","n_1_10_split","n_1_20_split"],"clause_id":"C1","subclause_id":"C1.2.2","phrase_version":"phrase_tree.v1"},{"ref_key":"Leviticus/15/14","word_index":10,"surface":"יוֹנָ֑ה","primary_accent":{"word_index":10,"class":"DISJUNCTIVE","codepoint":"U+0591","name":"etnahta","precedence":2,"observed_teamim":["U+0591"]},"phrase_role":"SPLIT","phrase_path":["w_10","n_9_10_join","n_7_10_split","n_1_10_split","n_1_20_split"],"clause_id":"C1","subclause_id":"C1.2.2","phrase_version":"phrase_tree.v1"},{"ref_key":"Leviticus/15/14","word_index":11,"surface":"וּבָ֣א","primary_accent":{"word_index":11,"class":"CONJUNCTIVE","codepoint":"U+05A3","name":"munach","precedence":1,"observed_teamim":["U+05A3"]},"phrase_role":"JOIN","phrase_path":["w_11","n_11_12_join","n_11_13_join","n_11_17_split","n_11_20_split","n_1_20_split"],"clause_id":"C2","subclause_id":"C2.1.1","phrase_version":"phrase_tree.v1"},{"ref_key":"Leviticus/15/14","word_index":12,"surface":"לִפְנֵ֣י","primary_accent":{"word_index":12,"class":"CONJUNCTIVE","codepoint":"U+05A3","name":"munach","precedence":1,"observed_teamim":["U+05A3"]},"phrase_role":"JOIN","phrase_path":["w_12","n_11_12_join","n_11_13_join","n_11_17_split","n_11_20_split","n_1_20_split"],"clause_id":"C2","subclause_id":"C2.1.1","phrase_version":"phrase_tree.v1"},{"ref_key":"Leviticus/15/14","word_index":13,"surface":"יְהֹוָ֗ה","primary_accent":{"word_index":13,"class":"DISJUNCTIVE","codepoint":"U+0597","name":"revia","precedence":2,"observed_teamim":["U+0597"]},"phrase_role":"SPLIT","phrase_path":["w_13","n_11_13_join","n_11_17_split","n_11_20_split","n_1_20_split"],"clause_id":"C2","subclause_id":"C2.1.1","phrase_version":"phrase_tree.v1"},{"ref_key":"Leviticus/15/14","word_index":14,"surface":"אֶל","primary_accent":{"word_index":14,"class":"NONE","codepoint":null,"name":null,"precedence":0,"observed_teamim":[]},"phrase_role":"JOIN","phrase_path":["w_14","n_14_15_join","n_14_17_split","n_11_17_split","n_11_20_split","n_1_20_split"],"clause_id":"C2","subclause_id":"C2.1.2.1","phrase_version":"phrase_tree.v1"},{"ref_key":"Leviticus/15/14","word_index":15,"surface":"פֶּ֙תַח֙","primary_accent":{"word_index":15,"class":"DISJUNCTIVE","codepoint":"U+0599","name":"pashta","precedence":2,"observed_teamim":["U+0599"]},"phrase_role":"SPLIT","phrase_path":["w_15","n_14_15_join","n_14_17_split","n_11_17_split","n_11_20_split","n_1_20_split"],"clause_id":"C2","subclause_id":"C2.1.2.1","phrase_version":"phrase_tree.v1"},{"ref_key":"Leviticus/15/14","word_index":16,"surface":"אֹ֣הֶל","primary_accent":{"word_index":16,"class":"CONJUNCTIVE","codepoint":"U+05A3","name":"munach","precedence":1,"observed_teamim":["U+05A3"]},"phrase_role":"JOIN","phrase_path":["w_16","n_16_17_join","n_14_17_split","n_11_17_split","n_11_20_split","n_1_20_split"],"clause_id":"C2","subclause_id":"C2.1.2.2","phrase_version":"phrase_tree.v1"},{"ref_key":"Leviticus/15/14","word_index":17,"surface":"מוֹעֵ֔ד","primary_accent":{"word_index":17,"class":"DISJUNCTIVE","codepoint":"U+0594","name":"zaqef_qatan","precedence":2,"observed_teamim":["U+0594"]},"phrase_role":"SPLIT","phrase_path":["w_17","n_16_17_join","n_14_17_split","n_11_17_split","n_11_20_split","n_1_20_split"],"clause_id":"C2","subclause_id":"C2.1.2.2","phrase_version":"phrase_tree.v1"},{"ref_key":"Leviticus/15/14","word_index":18,"surface":"וּנְתָנָ֖ם","primary_accent":{"word_index":18,"class":"DISJUNCTIVE","codepoint":"U+0596","name":"tipcha","precedence":1,"observed_teamim":["U+0596"]},"phrase_role":"SPLIT","phrase_path":["w_18","n_18_20_split","n_11_20_split","n_1_20_split"],"clause_id":"C2","subclause_id":"C2.2.1","phrase_version":"phrase_tree.v1"},{"ref_key":"Leviticus/15/14","word_index":19,"surface":"אֶל","primary_accent":{"word_index":19,"class":"NONE","codepoint":null,"name":null,"precedence":0,"observed_teamim":[]},"phrase_role":"JOIN","phrase_path":["w_19","n_19_20_join","n_18_20_split","n_11_20_split","n_1_20_split"],"clause_id":"C2","subclause_id":"C2.2.2","phrase_version":"phrase_tree.v1"},{"ref_key":"Leviticus/15/14","word_index":20,"surface":"הַכֹּהֵן","primary_accent":{"word_index":20,"class":"NONE","codepoint":null,"name":null,"precedence":0,"observed_teamim":[]},"phrase_role":"TAIL","phrase_path":["w_20","n_19_20_join","n_18_20_split","n_11_20_split","n_1_20_split"],"clause_id":"C2","subclause_id":"C2.2.2","phrase_version":"phrase_tree.v1"}]}
